LICENSE
MANIFEST.in
README.md
requirements.txt
setup.py
django_sunshine.egg-info/PKG-INFO
django_sunshine.egg-info/SOURCES.txt
django_sunshine.egg-info/dependency_links.txt
django_sunshine.egg-info/requires.txt
django_sunshine.egg-info/top_level.txt
sunshine/__init__.py
sunshine/__version__.py
sunshine/admin.py
sunshine/apps.py
sunshine/collab.py
sunshine/common.py
sunshine/context_processors.py
sunshine/forms.py
sunshine/models.py
sunshine/tests.py
sunshine/urls.py
sunshine/views.py
sunshine/management/commands/__init__.py
sunshine/management/commands/list_perms.py
sunshine/migrations/__init__.py
sunshine/static/.gitignore
sunshine/static/sunshine/css/sb-admin-2-dev.min.css
sunshine/static/sunshine/css/sb-admin-2-uat.min.css
sunshine/static/sunshine/css/sb-admin-2.min.css
sunshine/static/sunshine/images/local.png
sunshine/static/sunshine/images/prod.png
sunshine/static/sunshine/images/uat.png
sunshine/static/sunshine/js/common.js
sunshine/static/sunshine/js/sb-admin-2.js
sunshine/static/sunshine/js/sb-admin-2.min.js
sunshine/static/vendor/bootstrap/css/bootstrap-grid.min.css
sunshine/static/vendor/bootstrap/css/bootstrap-reboot.min.css
sunshine/static/vendor/bootstrap/css/bootstrap.min.css
sunshine/static/vendor/bootstrap/js/bootstrap.bundle.min.js
sunshine/static/vendor/bootstrap/js/bootstrap.min.js
sunshine/static/vendor/faf/css/all.min.css
sunshine/static/vendor/faf/webfonts/fa-brands-400.eot
sunshine/static/vendor/faf/webfonts/fa-brands-400.svg
sunshine/static/vendor/faf/webfonts/fa-brands-400.ttf
sunshine/static/vendor/faf/webfonts/fa-brands-400.woff
sunshine/static/vendor/faf/webfonts/fa-brands-400.woff2
sunshine/static/vendor/faf/webfonts/fa-regular-400.eot
sunshine/static/vendor/faf/webfonts/fa-regular-400.svg
sunshine/static/vendor/faf/webfonts/fa-regular-400.ttf
sunshine/static/vendor/faf/webfonts/fa-regular-400.woff
sunshine/static/vendor/faf/webfonts/fa-regular-400.woff2
sunshine/static/vendor/faf/webfonts/fa-solid-900.eot
sunshine/static/vendor/faf/webfonts/fa-solid-900.svg
sunshine/static/vendor/faf/webfonts/fa-solid-900.ttf
sunshine/static/vendor/faf/webfonts/fa-solid-900.woff
sunshine/static/vendor/faf/webfonts/fa-solid-900.woff2
